biofoundry/__init__.py
biofoundry/tools.py
biofoundry-0.1.0.dist-info/licenses/LICENSE
biofoundry-0.1.0.dist-info/METADATA
biofoundry-0.1.0.dist-info/WHEEL
biofoundry-0.1.0.dist-info/top_level.txt
biofoundry-0.1.0.dist-info/RECORD
