Metadata-Version: 2.4
Name: biofoundry
Version: 0.1.0
Summary: Tool for the biofoundry abstraction hierarchy framework
Author: Peter Vegh
License-Expression: MIT
Project-URL: Homepage, https://github.com/Edinburgh-Genome-Foundry/biofoundry
Keywords: biology,biofoundry
License-File: LICENSE
Dynamic: license-file
